miose_toolkit_db/__init__.py
miose_toolkit_db/db_url.py
miose_toolkit_db/orm.py
miose_toolkit_db-0.2.2.dist-info/METADATA
miose_toolkit_db-0.2.2.dist-info/WHEEL
miose_toolkit_db-0.2.2.dist-info/entry_points.txt
miose_toolkit_db-0.2.2.dist-info/RECORD
