Metadata-Version: 2.1
Name: miose-toolkit-db
Version: 0.2.2
Summary: Miose Toolkit 数据库模块
Author: KroMiose
Author-email: li_xiangff@163.com
Requires-Python: >=3.8,<3.12
Classifier: Programming Language :: Python :: 3
Classifier: Programming Language :: Python :: 3.8
Classifier: Programming Language :: Python :: 3.9
Classifier: Programming Language :: Python :: 3.10
Classifier: Programming Language :: Python :: 3.11
Requires-Dist: pymysql (>=1.1.0,<2.0.0)
Requires-Dist: sqlalchemy (>=2.0.23,<3.0.0)
